tresbackup/__init__.py
tresbackup/__main__.py
tresbackup/backup.py
tresbackup-0.0.4.dist-info/LICENSE
tresbackup-0.0.4.dist-info/METADATA
tresbackup-0.0.4.dist-info/WHEEL
tresbackup-0.0.4.dist-info/entry_points.txt
tresbackup-0.0.4.dist-info/top_level.txt
tresbackup-0.0.4.dist-info/RECORD
