Metadata-Version: 2.1
Name: tresbackup
Version: 0.0.4
Summary: CLI for easy ES backup and restore with simple tracking of non-modified indexes
Home-page: https://github.com/Stranger65536/tresbackup
Author: Stranger65536
Author-email: stranger.65536@gmail.com
License: MIT
Classifier: License :: OSI Approved :: GNU Affero General Public License v3 or later (AGPLv3+)
Classifier: Programming Language :: Python :: 3
Classifier: Programming Language :: Python :: 3.7
Requires-Python: >=3.7
License-File: LICENSE
Requires-Dist: elasticsearch (==7.10.1)
Requires-Dist: argparse (==1.4.0)
Requires-Dist: dataclasses-json (==0.5.7)
Requires-Dist: zipstream-ng (==1.4.0)
Requires-Dist: tqdm (==4.64.1)
Requires-Dist: stream-unzip (==0.0.83)
Requires-Dist: ijson (~=3.2.0.post0)
